simbaDriver-1.0.0.data/scripts/SIMBA.py
simbadriver/__init__.py
simbadriver/configuration.py
simbadriver/module.py
simbadriver/parslModule.py
simbadriver/rfc3339Duration.py
simbadriver/scheduler.py
simbadriver/simbadriver.py
simbaDriver-1.0.0.dist-info/LICENSE
simbaDriver-1.0.0.dist-info/METADATA
simbaDriver-1.0.0.dist-info/WHEEL
simbaDriver-1.0.0.dist-info/top_level.txt
simbaDriver-1.0.0.dist-info/RECORD
