Metadata-Version: 2.1
Name: simbaDriver
Version: 1.0.0
Summary: SIMBA is a framework for performing multi-scale simulations in an HPC environment.
Home-page: https://simba-driver.readthedocs.io/en/latest/index.html
Author: Stefan Hoops
Author-email: shoops@virginia.edu
License: Apache 2.0
Classifier: Programming Language :: Python :: 3
Classifier: License :: OSI Approved :: Apache Software License
Classifier: Operating System :: OS Independent
License-File: LICENSE
Requires-Dist: jsonschema
Requires-Dist: parsl
